Workbook

Sheet 预算总览
A1: 装修需求与预算
A2: 约80㎡旧房全拆｜装修公司全包｜两人居住｜大家电优先小米/米家｜2026-10-06
A4: 金额为规划预留，单位：人民币元。未扣补贴、券或以旧换新；窗户与柜体未量尺寸。蓝色格可改，合计自动更新；采购阶段在预算明细调整。
A6: 资金分组 | B6: 低位估算 | C6: 高位估算 | D6: 当前预留 | E6: 范围与口径
A7: 全包基础 | B7: =SUMIFS(预算明细!E6:E45,预算明细!B6:B45,A7,预算明细!I6:I45,1) -> 53100 | C7: =SUMIFS(预算明细!F6:F45,预算明细!B6:B45,A7,预算明细!I6:I45,1) -> 79000 | D7: =SUMIFS(预算明细!G6:G45,预算明细!B6:B45,A7,预算明细!I6:I45,1) -> 65200 | E7: 拆旧、水电、防水基层、瓷砖墙顶、门、橱柜卫浴与基础收纳；全包施工管理是否已含，见报价对照。
A8: 门窗补充 | B8: =SUMIFS(预算明细!E6:E45,预算明细!B6:B45,A8,预算明细!I6:I45,1) -> 10100 | C8: =SUMIFS(预算明细!F6:F45,预算明细!B6:B45,A8,预算明细!I6:I45,1) -> 17500 | D8: =SUMIFS(预算明细!G6:G45,预算明细!B6:B45,A8,预算明细!I6:I45,1) -> 13000 | E8: 全换外窗、新入户门、猫用窗户防护；单列金额以核对套餐包含范围，合计只计一次。
A9: 灯具窗帘智能 | B9: =SUMIFS(预算明细!E6:E45,预算明细!B6:B45,A9,预算明细!I6:I45,1) -> 3800 | C9: =SUMIFS(预算明细!F6:F45,预算明细!B6:B45,A9,预算明细!I6:I45,1) -> 7000 | D9: =SUMIFS(预算明细!G6:G45,预算明细!B6:B45,A9,预算明细!I6:I45,1) -> 5200 | E9: 基础照明面板、手拉窗帘、基础手机/语音控制；升级差价与普通件扣重。
A10: 首批家具 | B10: =SUMIFS(预算明细!E6:E45,预算明细!B6:B45,A10,预算明细!I6:I45,1) -> 9300 | C10: =SUMIFS(预算明细!F6:F45,预算明细!B6:B45,A10,预算明细!I6:I45,1) -> 16500 | D10: =SUMIFS(预算明细!G6:G45,预算明细!B6:B45,A10,预算明细!I6:I45,1) -> 12800 | E10: 主卧床、沙发、餐桌、双电脑桌、补一把电脑椅、梳妆台、入住杂项。
A11: 首批家电 | B11: =SUMIFS(预算明细!E6:E45,预算明细!B6:B45,A11,预算明细!I6:I45,1) -> 10300 | C11: =SUMIFS(预算明细!F6:F45,预算明细!B6:B45,A11,预算明细!I6:I45,1) -> 15800 | D11: =SUMIFS(预算明细!G6:G45,预算明细!B6:B45,A11,预算明细!I6:I45,1) -> 13100 | E11: 主卧空调、冰箱、洗烘一体、烟灶、燃气热水器、安装辅材及少量小电器。
A12: 舒适后补 | B12: =SUMIFS(预算明细!E6:E45,预算明细!B6:B45,A12,预算明细!I6:I45,1) -> 8000 | C12: =SUMIFS(预算明细!F6:F45,预算明细!B6:B45,A12,预算明细!I6:I45,1) -> 12500 | D12: =SUMIFS(预算明细!G6:G45,预算明细!B6:B45,A12,预算明细!I6:I45,1) -> 9600 | E12: 客厅空调、电视、自动上下水机器人；冬夏入住时客厅空调可提前到首批。
A13: 后买低频 | B13: =SUMIFS(预算明细!E6:E45,预算明细!B6:B45,A13,预算明细!I6:I45,1) -> 3500 | C13: =SUMIFS(预算明细!F6:F45,预算明细!B6:B45,A13,预算明细!I6:I45,1) -> 5800 | D13: =SUMIFS(预算明细!G6:G45,预算明细!B6:B45,A13,预算明细!I6:I45,1) -> 4400 | E13: 洗碗机、次卧客床；机器后买，接口与位置装修时先确定。
A14: 可选未计 | B14: =SUMIFS(预算明细!E6:E45,预算明细!B6:B45,A14,预算明细!I6:I45,1) -> 0 | C14: =SUMIFS(预算明细!F6:F45,预算明细!B6:B45,A14,预算明细!I6:I45,1) -> 0 | D14: =SUMIFS(预算明细!G6:G45,预算明细!B6:B45,A14,预算明细!I6:I45,1) -> 0 | E14: 只汇总“计入”改为1的备选项目，初始金额为0。各项估算见预算明细；0表示未选，不表示免费。
A16: 首批项目小计 | B16: =SUMIFS(预算明细!E6:E45,预算明细!H6:H45,"首批",预算明细!I6:I45,1) -> 86600 | C16: =SUMIFS(预算明细!F6:F45,预算明细!H6:H45,"首批",预算明细!I6:I45,1) -> 135800 | D16: =SUMIFS(预算明细!G6:G45,预算明细!H6:H45,"首批",预算明细!I6:I45,1) -> 109300 | E16: 首批基本入住，不含后补设备。
A17: 首批机动资金（10%） | B17: =CEILING(B16*10%,100) -> 8700 | C17: =CEILING(C16*10%,100) -> 13600 | D17: =CEILING(D16*10%,100) -> 11000 | E17: 旧房拆后基层、辅材和实测工程量可能变化，机动只计一次。
A18: 首批＋机动 | B18: =B16+B17 -> 95300 | C18: =C16+C17 -> 149400 | D18: =D16+D17 -> 120300 | E18: 用于安排首批现金；当前预留为各项目规划值，非预算上限。
A20: 后续采购小计 | B20: =SUMIF(预算明细!I6:I45,1,预算明细!E6:E45)-B16 -> 11500 | C20: =SUMIF(预算明细!I6:I45,1,预算明细!F6:F45)-C16 -> 18300 | D20: =SUMIF(预算明细!I6:I45,1,预算明细!G6:G45)-D16 -> 14000 | E20: 客厅空调、电视、机器人、洗碗机、客床。
A21: 首批＋后续＋机动 | B21: =B18+B20 -> 106800 | C21: =C18+C20 -> 167700 | D21: =D18+D20 -> 134300 | E21: 不含下方可选项、电脑硬件、游戏主机和可退装修押金。
A24: 未纳入合计的备选：次卧空调、净水器、智能门锁升级、电动窗帘后升级。电脑硬件按用户要求暂不采购；Switch等娱乐硬件另行考虑。
A26: 全包询价：请每家公司按同一范围列明拆旧清运、全部门窗、柜体五金、开关灯具、安装收口和管理服务是否包含。已在套餐计入的项目无需再加。
A28: 图上标注面积合计54.4㎡，不是已核实的套内面积；主卧2.83×3.37m、次卧2.55×3.14m。铺贴、涂刷、窗户和柜体统一按现场测量工程量报价。

Sheet 确认需求
A1: 已确认的装修需求
A2: 以本次问答的最新选择为准；“方案建议”和“待复核”与用户已确定事项分别标明。
A4: 旧房全拆重做；保留其他分隔，仅拆客厅后加隔间。使用需求已够形成第一版方案，尺寸与旧基层情况由现场复尺补齐。
A5: 区域 | B5: 事项 | C5: 具体需求 | D5: 确认状态
A6: 总体 | B6: 总预算 | C6: 暂不设最高额度，先算必需项目。 | D6: 用户确认
A7: 总体 | B7: 施工方式 | C7: 装修公司全包：主材与施工由装修公司负责；报价须明确具体范围。 | D7: 用户确认
A8: 总体 | B8: 工期 | C8: 没有固定入住期限，不赶着入住。 | D8: 用户确认
A9: 总体 | B9: 旧房处理 | C9: 已有装修，旧装修全部拆除重做。 | D9: 用户确认
A10: 总体 | B10: 布局 | C10: 拆客厅里后加的隔间，恢复客餐厅；其他房间分隔保留。 | D10: 用户确认
A11: 总体 | B11: 门窗 | C11: 外窗全部换新；入户门也换新。 | D11: 用户确认
A12: 总体 | B12: 搬运 | C12: 有电梯，可用于装修搬运。 | D12: 用户确认
A13: 居住 | B13: 人数 | C13: 两个人长期住，都睡主卧。 | D13: 用户确认
A14: 居住 | B14: 家电品牌 | C14: 大家电尽量选小米/米家，允许分批采购。 | D14: 用户确认
A15: 居住 | B15: 基本风格 | C15: 装饰从简；按简单墙顶和成品家具优先规划。 | D15: 原需求＋方案假设
A16: 主卧 | B16: 身材与床 | C16: 188cm/100kg、160cm/50kg；助手建议床宽1.8m，床长优先2.1m。 | D16: 身材已确认；床为方案建议
... A39: 机器人 | B39: 基础条件 | C39: 计划自动换水扫拖机器人，先留基站、上下水、电源与检修空间。 | D39: 原需求文件

Sheet 预算明细
A1: 逐项预算与采购范围
A2: 蓝色“当前预留”“阶段”“计入”可以改；1=计入、0=未计。调整阶段会更新首批与后补现金安排；合同报价填“报价对照”。
A4: 全包范围不靠名称判断：按分项清单核对。家具、家电作为采购预算；门窗、收纳等如全包套餐已含，以实际分项金额替换，避免重复。
A5: 编号 | B5: 资金分组 | C5: 项目 | D5: 计划范围 | E5: 低位估算 | F5: 高位估算 | G5: 当前预留 | H5: 阶段 | I5: 计入(1/0) | J5: 报价核对点
A6: 1 | B6: 全包基础 | C6: 全拆旧与垃圾清运 | D6: 旧地面、厨卫墙砖、旧橱柜洁具、旧门套等；拆客厅后加隔间，其他布局保留。 | E6: 6000 | F6: 9000 | G6: 7500 | H6: 首批 | I6: 1 | J6: 列明拆除范围、装袋、下楼、外运及清运次数；电梯可用。原家具清走情况现场核对。
A7: 2 | B7: 全包基础 | C7: 水电重做及未来设备预留 | D7: 按新布局重做；靠阳台两侧单屏工位的插座网口，空调点位，洗烘机、洗碗机、机器人接口，电动窗帘电源。 | E7: 8000 | F7: 11000 | G7: 9500 | H7: 首批 | I7: 1 | J7: 列点位图、回路、水管电线品牌规格及计价方式；窗边桌线缆走墙，避开窗帘和阳台门。此项含管线底盒，面板另核算。
A8: 3 | B8: 全包基础 | C8: 防水、找平及基层修复 | D8: 拆除后的墙地面修复、必要找平、厨卫需做的防水与施工检验。 | E8: 4500 | F8: 7500 | G8: 6000 | H8: 首批 | I8: 1 | J8: 区分拆除、修复、防水和铺砖工序，避免同一找平工程重复计价；旧基层状态拆后复核。
A9: 4 | B9: 全包基础 | C9: 瓷砖、铺贴及收口 | D9: 客厅与两卧均铺瓷砖；厨卫墙地砖、阳台地面按实测；含辅料、踢脚线及填缝收口。 | E9: 11000 | F9: 15000 | G9: 13000 | H9: 首批 | I9: 1 | J9: 按净铺贴面积报价，列品牌型号、损耗、铺贴规格、辅料与收口；54.4㎡只是图上已标房间面积合计。
A10: 5 | B10: 全包基础 | C10: 墙顶基层与乳胶漆 | D10: 简单墙顶面处理及乳胶漆，不做复杂背景墙。 | E10: 5500 | F10: 8000 | G10: 6500 | H10: 首批 | I10: 1 | J10: 列施工面积、基层处理方式、腻子及涂料型号；墙皮铲除若在拆旧中已计，不重复加。
A11: 6 | B11: 全包基础 | C11: 厨卫吊顶及必要局部吊顶 | D11: 厨卫基础吊顶及必要遮管，整体从简。 | E11: 1800 | F11: 3000 | G11: 2200 | H11: 首批 | I11: 1 | J11: 主卧顶柜另在收纳项；复杂客厅造型未列入。
A12: 7 | B12: 全包基础 | C12: 室内门及门套 | D12: 两卧、卫生间及厨房需更换的门，暂按3～4樘估算。 | E12: 3500 | F12: 5500 | G12: 4500 | H12: 首批 | I12: 1 | J12: 实测数量，列门扇门套、五金、门槛和安装；入户门另列。
A13: 8 | B13: 全包基础 | C13: 橱柜、台面、水槽与龙头 | D13: 约4.7㎡厨房，基础地柜吊柜、台面、水槽龙头；洗碗机以后买，预留柜位。 | E13: 6500 | F13: 9500 | G13: 8000 | H13: 首批 | I13: 1 | J13: 列地柜吊柜长度、转角、台面、五金和安装；柜位必须按拟选洗碗机外尺寸确定。
A14: 9 | B14: 全包基础 | C14: 基础卫浴 | D14: 蹲便器及水箱、花洒、洗手盆/小浴室柜、地漏和基础配件；开放式淋浴。 | E14: 2800 | F14: 4500 | G14: 3500 | H14: 首批 | I14: 1 | J14: 蹲便形式保留；便器设备按新购预留，旧件是否能复用现场核对。防水和管线在对应工种项。
A15: 10 | B15: 全包基础 | C15: 主卧及基础收纳 | D15: 原需求主卧顶柜＋挂衣杆＋帘子，鞋柜及基础储物；先按两人日常衣物量规划。新增浅顶柜另列备选。 | E15: 3500 | F15: 6000 | G15: 4500 | H15: 首批 | I15: 1 | J15: 列柜体计价方式、板材五金、墙体固定；梳妆台在家具项。主卧原顶柜已计此行，不能在新增顶柜中重复报价。
A16: 11 | B16: 门窗补充 | C16: 外窗全部换新 | D16: 现有外窗全部更换；面积及开启方式尚未实测。 | E16: 7000 | F16: 12000 | G16: 9000 | H16: 首批 | I16: 1 | J16: 预算占位，按每樘窗尺寸、型材玻璃、拆旧安装、密封收口核算；新增封阳台工程范围需现场明确。
A17: 12 | B17: 门窗补充 | C17: 入户门换新 | D17: 新入户门、常规配套锁具、拆旧安装与收口。 | E17: 2500 | F17: 4000 | G17: 3000 | H17: 首批 | I17: 1 | J17: 此行按普通配套锁估算；智能锁是否升级未确认，另作可选差价。
... A45: 40 | B45: 可选未计 | C45: 新增浅顶柜（方案备选） | D45: 两个工位上方、电视墙上方、主卧门洞上方及次卧柜补顶层，共约5.48延米；前四处深30cm，次卧延续50cm深。 | E45: 2500 | F45: 5500 | G45: 3500 | H45: 首批 | I45: 0 | J45: 规划估算，未取得柜体报价；需按板材五金、墙体可靠固定、梁和门窗空调净空复尺。主卧原顶柜已计基础收纳，勿重复。
C46: 计入项目合计 | E46: =SUMIF(I6:I45,1,E6:E45) -> 98100 | F46: =SUMIF(I6:I45,1,F6:F45) -> 154100 | G46: =SUMIF(I6:I45,1,G6:G45) -> 123300 | J46: 不含机动资金；机动资金在“预算总览”只计一次。

Sheet 采购节奏
A1: 施工与分批采购
A2: 没有硬性入住期限；先定布局、尺寸和接口，设备按需要买，避免尺寸变化导致返工。
A5: 阶段 | B5: 安排 | C5: 必须先定的条件 | D5: 对应预算
A6: 方案及询价 | B6: 复尺窗边两侧单屏工位、折叠餐桌、沙发电视区、床调向、浅顶柜、门窗与洗衣区。 | C6: 设备购买可延后，但冰箱、洗烘机、洗碗机、机器人等拟选型号的外尺寸与安装条件需先确定。 | D6: 全包基础＋门窗补充
A7: 拆旧及水电 | B7: 拆旧、复核旧基层、完成点位图与水电防水等隐蔽工程。 | C7: 两台电脑回路与网口、空调点位、电动窗帘电源、洗碗机和机器人接口一次规划。 | D7: 全包基础
A8: 硬装安装完成 | B8: 完成瓷砖墙顶、门窗、橱柜卫浴、收纳、照明和手拉窗帘。 | C8: 各分项安装收口责任在报价里明确，家电进场顺序与装修公司协调。 | D8: 全包基础＋门窗灯具窗帘
A9: 基本入住 | B9: 主卧床和日常家具；主卧空调、冰箱、洗烘一体机、烟灶、热水器。 | C9: 用现成电脑椅、空气炸锅、电饭锅；另一把电脑椅与双桌按布局补齐。 | D9: 首批家具＋首批家电
A10: 优先后补 | B10: 客厅空调、电视、自动上下水机器人。 | C10: 客厅常用且有两台电脑；冬夏入住将客厅空调提前。电视与游戏主机位置先留。 | D10: 舒适后补
A11: 低频后买 | B11: 洗碗机、次卧客床。 | C11: 一年少量留宿；床形式在工位位置最终确定后选择。洗碗机位置已预留。 | D11: 后买低频
A12: 按需升级 | B12: 次卧空调、净水器、智能锁、电动窗帘；新增浅顶柜先确定是否随硬装做。 | C12: 这些是备选，当前合计未包含；确认购买再把“计入”改为1。 | D12: 可选未计

Sheet 报价对照
A1: 装修公司全包报价对照
A2: 填写A/B/C公司分项金额与包含范围；同一范围对比。蓝色格填写实际报价，基准为“预算明细”的当前预留。
A4: 本页只比较施工主材及门窗补充。请装修公司把设计、管理、成品保护、运输、安装、清运是否已含写清；额外服务费另列，已有包含项只计一次。
A5: 项目 | B5: 统一范围 | C5: 规划预留 | D5: 公司A金额 | E5: 公司A范围/型号 | F5: 公司B金额 | G5: 公司B范围/型号 | H5: 公司C金额 | I5: 公司C范围/型号
A6: 全拆旧与垃圾清运 | B6: 旧地面、厨卫墙砖、旧橱柜洁具、旧门套等；拆客厅后加隔间，其他布局保留。 | C6: =预算明细!G6 -> 7500
A7: 水电重做及未来设备预留 | B7: 按新布局重做；靠阳台两侧单屏工位的插座网口，空调点位，洗烘机、洗碗机、机器人接口，电动窗帘电源。 | C7: =预算明细!G7 -> 9500
A8: 防水、找平及基层修复 | B8: 拆除后的墙地面修复、必要找平、厨卫需做的防水与施工检验。 | C8: =预算明细!G8 -> 6000
A9: 瓷砖、铺贴及收口 | B9: 客厅与两卧均铺瓷砖；厨卫墙地砖、阳台地面按实测；含辅料、踢脚线及填缝收口。 | C9: =预算明细!G9 -> 13000
A10: 墙顶基层与乳胶漆 | B10: 简单墙顶面处理及乳胶漆，不做复杂背景墙。 | C10: =预算明细!G10 -> 6500
A11: 厨卫吊顶及必要局部吊顶 | B11: 厨卫基础吊顶及必要遮管，整体从简。 | C11: =预算明细!G11 -> 2200
A12: 室内门及门套 | B12: 两卧、卫生间及厨房需更换的门，暂按3～4樘估算。 | C12: =预算明细!G12 -> 4500
A13: 橱柜、台面、水槽与龙头 | B13: 约4.7㎡厨房，基础地柜吊柜、台面、水槽龙头；洗碗机以后买，预留柜位。 | C13: =预算明细!G13 -> 8000
A14: 基础卫浴 | B14: 蹲便器及水箱、花洒、洗手盆/小浴室柜、地漏和基础配件；开放式淋浴。 | C14: =预算明细!G14 -> 3500
A15: 主卧及基础收纳 | B15: 原需求主卧顶柜＋挂衣杆＋帘子，鞋柜及基础储物；先按两人日常衣物量规划。新增浅顶柜另列备选。 | C15: =预算明细!G15 -> 4500
A16: 外窗全部换新 | B16: 现有外窗全部更换；面积及开启方式尚未实测。 | C16: =预算明细!G16 -> 9000
A17: 入户门换新 | B17: 新入户门、常规配套锁具、拆旧安装与收口。 | C17: =预算明细!G17 -> 3000
... A21: 基础智能与网络设备 | B21: 米家方向；手机、语音控制，基础音箱/网关/路由器和必要智能开关升级差价。 | C21: =预算明细!G21 -> 1200
A22: 额外设计/管理/运输等服务费 | B22: 先核对是否已包含在分项或套餐；未包含的服务写范围后填写。 | C22: 0
A23: 同口径报价合计 | B23: 未填写全部必需范围前，合计只是已填金额；未报价/漏项不等于免费。 | C23: =SUM(C6:C22) -> 83400 | D23: =IF(COUNT(D6:D22)=0,"",SUM(D6:D22)) | F23: =IF(COUNT(F6:F22)=0,"",SUM(F6:F22)) | H23: =IF(COUNT(H6:H22)=0,"",SUM(H6:H22))
A25: 备选：新增浅顶柜 | B25: 单独报新增五处柜体价格，原主卧顶柜扣重；本行不计入上方同口径必需报价合计。 | C25: =预算明细!G45 -> 3500

Sheet 依据与实测
A1: 资料依据与现场待核
A2: 本表预算是按需求拆项的规划估算；未获得装修公司现场报价，品牌与具体型号尚未最终选择。
A5: 依据/事项 | B5: 内容 | C5: 状态 | D5: 来源或处理方式
A6: 已标面积 | B6: 次卧8.03、主卧9.94、客餐厅25.6、厨房4.7、卫生间2.79、阳台3.34㎡，合计54.4㎡。约80㎡为用户给出的整房概况，不能直接等同施工净面积。 | C6: 图面资料，非实测 | D6: https://github.com/Shengshenlan/zhuangxiu/blob/main/户型尺寸.json
A7: 户型与净高 | B7: 主卧2.83×3.37m，次卧2.55×3.14m；厨房2.06×2.15m，阳台3.05×1.09m；净高约2.7m。 | C7: 尺寸图＋用户自述 | D7: https://github.com/Shengshenlan/zhuangxiu/blob/main/用户提供/带尺寸户型图.jpg
A8: 原始需求 | B8: 简装、顶柜挂衣杆帘子、猫活动、机器人上下水、主卧梳妆台；新问答更新了人数、工位、洗烘一体与卫生间方式。 | C8: 本次问答优先 | D8: https://github.com/Shengshenlan/zhuangxiu/blob/main/user_demand.md
A9: 小米家电范围 | B9: 已核对小米官网的1.5匹空调与洗烘12kg产品；官网页面存在促销及导航标价变化，预算按范围预留，不是当天到手价。 | C9: 2026-10-06检索 | D9: https://www.mi.com/mijia-wash-dryers/clean-pro-10kg
A10: 洗烘一体机产品 | B10: 米家洗衣机 洗烘12kg，官方购买页用于确认产品类型；本表不以旧单洗款代替洗烘一体预算。 | C10: 产品类型核验 | D10: https://www.mi.com/shop/buy/detail?product_id=21556
A11: 卧室空调产品 | B11: 巨省电 1.5匹新一级能效 小米空调官方购买页；具体能效、型号、外机位置与安装费用下单时再核对。 | C11: 产品方向核验 | D11: https://www.mi.com/shop/buy/detail?product_id=13143
A12: 床架外尺寸例子 | B12: 宜家松耶桑德：床垫180×200cm，床架外尺寸193×207cm。此项是尺寸核对示例，不代表已选此款。 | C12: 官方尺寸说明 | D12: https://www.ikea.cn/cn/zh/p/songesand-bed-frame-white-60372511/
A13: 预算取值 | B13: 低/高位为普通档简装规划范围；当前预留为逐项规划值；首批机动10%，向上取整至100元。费用没有套用未经核实的80㎡套餐单价。 | C13: 助手规划估算 | D13: 以现场工程量、品牌规格、统一范围全包报价替换；不是市场统一收费标准。
A14: 全包服务计价 | B14: 施工管理、设计、成品保护及协调是否已在报价分项内需写清；若另收费，在报价对照单独填入，不与已含项目重复。 | C14: 公司报价时确认 | D14: 预算范围按常规简装总体占位；额外收费会占用机动资金，超过时需调整总额。
A15: 客餐厅工位布局 | B15: 两台台式机各一屏；桌子靠阳台两侧墙，中间约82cm通路以58cm椅子收近为前提。餐桌折叠并移出展开。 | C15: 2026-10-06第2版；待复尺 | D15: 屏幕侧对窗，窗帘控制反光；测实际椅子、窗帘、门洞、线缆和主机。
A16: 窗边工位采光 | B16: 屏幕与窗面尽量成直角，配窗帘调节反光；采用侧向来光的排布。 | C16: 官方工位环境建议 | D16: https://www.osha.gov/etools/computer-workstations/workstation-environment
... A22: 费用之外的现金 | B22: 可退装修押金、搬家运费、过渡居住开支、物业实际收费未获取，本表未计；金额确认后可另加。 | C22: 尚无实际金额 | D22: 可退押金属于临时现金占用；不可退项目按具体收费填入。
